LICENSE
MANIFEST.in
README.md
petl_django.py
setup.py
petl_django.egg-info/PKG-INFO
petl_django.egg-info/SOURCES.txt
petl_django.egg-info/dependency_links.txt
petl_django.egg-info/requires.txt
petl_django.egg-info/top_level.txt